cli/__init__.py
cli/cli.py
syntropi_download-0.11.dist-info/METADATA
syntropi_download-0.11.dist-info/WHEEL
syntropi_download-0.11.dist-info/entry_points.txt
syntropi_download-0.11.dist-info/top_level.txt
syntropi_download-0.11.dist-info/RECORD
