Metadata-Version: 2.1
Name: syntropi-download
Version: 0.11
Requires-Dist: click
Requires-Dist: requests
Requires-Dist: python-dotenv
